mdmrgraph/__init__.py
mdmrgraph/graph.py
mdmrgraph/utils.py
mdmr_graph-0.0.2.dist-info/LICENSE
mdmr_graph-0.0.2.dist-info/METADATA
mdmr_graph-0.0.2.dist-info/WHEEL
mdmr_graph-0.0.2.dist-info/top_level.txt
mdmr_graph-0.0.2.dist-info/RECORD
