Metadata-Version: 2.1
Name: mdmr-graph
Version: 0.0.2
Summary: Simple Multi-Dimentional Multi-resolution graph for building sketches
Home-page: https://github.com/Simonl07/mdmr-graph
Author: Simon Lu
Author-email: mlu18@dons.usfca.edu
License: UNKNOWN
Platform: UNKNOWN
Classifier: Development Status :: 1 - Planning
Classifier: Intended Audience :: Science/Research
Classifier: License :: OSI Approved :: MIT License
Classifier: Programming Language :: Python :: 3
